LICENSE
README.md
setup.py
nameko_kafka/__init__.py
nameko_kafka/constants.py
nameko_kafka/dependency.py
nameko_kafka/entrypoint.py
nameko_kafka/version.py
nameko_kafka.egg-info/PKG-INFO
nameko_kafka.egg-info/SOURCES.txt
nameko_kafka.egg-info/dependency_links.txt
nameko_kafka.egg-info/requires.txt
nameko_kafka.egg-info/top_level.txt
nameko_kafka/consumers/__init__.py
nameko_kafka/consumers/default.py
nameko_kafka/consumers/exactly_once.py
nameko_kafka/consumers/least_once.py
nameko_kafka/consumers/most_once.py
nameko_kafka/storage/__init__.py
nameko_kafka/storage/base.py
nameko_kafka/storage/mongo.py
tests/test_dependency.py
tests/test_entrypoint.py
tests/test_consumers/__init__.py
tests/test_consumers/test_default.py
tests/test_consumers/test_exactly_once.py
tests/test_consumers/test_least_once.py
tests/test_consumers/test_most_once.py
tests/test_storage/__init__.py
tests/test_storage/test_base.py
tests/test_storage/test_mongo.py