Metadata-Version: 2.1
Name: nameko-kafka
Version: 0.2.1
Summary: Kafka extension for Nameko microservice framework
Home-page: https://github.com/ketgo/nameko-kafka
Author: Ketan Goyal
Author-email: ketangoyal1988@gmail.com
License: MIT
Keywords: nameko,kafka,microservice
Classifier: Intended Audience :: Developers
Classifier: License :: OSI Approved :: Apache Software License
Classifier: Operating System :: OS Independent
Classifier: Topic :: Internet
Classifier: Topic :: Software Development :: Libraries :: Python Modules
Classifier: Natural Language :: English
Classifier: Programming Language :: Python
Classifier: Programming Language :: Python :: 3.5
Classifier: Programming Language :: Python :: 3.6
Classifier: Programming Language :: Python :: 3.7
Requires-Python: >=3.4
Provides-Extra: dev
Provides-Extra: mongo
Provides-Extra: sql
License-File: LICENSE
